docker-stubs/__init__.pyi
docker-stubs/_version.pyi
docker-stubs/api/__init__.pyi
docker-stubs/api/build.pyi
docker-stubs/api/client.pyi
docker-stubs/api/config.pyi
docker-stubs/api/container.pyi
docker-stubs/api/daemon.pyi
docker-stubs/api/exec_api.pyi
docker-stubs/api/image.pyi
docker-stubs/api/network.pyi
docker-stubs/api/plugin.pyi
docker-stubs/api/secret.pyi
docker-stubs/api/service.pyi
docker-stubs/api/swarm.pyi
docker-stubs/api/volume.pyi
docker-stubs/auth.pyi
docker-stubs/client.pyi
docker-stubs/constants.pyi
docker-stubs/context/__init__.pyi
docker-stubs/context/api.pyi
docker-stubs/context/config.pyi
docker-stubs/context/context.pyi
docker-stubs/credentials/__init__.pyi
docker-stubs/credentials/constants.pyi
docker-stubs/credentials/errors.pyi
docker-stubs/credentials/store.pyi
docker-stubs/credentials/utils.pyi
docker-stubs/errors.pyi
docker-stubs/models/__init__.pyi
docker-stubs/models/configs.pyi
docker-stubs/models/containers.pyi
docker-stubs/models/images.pyi
docker-stubs/models/networks.pyi
docker-stubs/models/nodes.pyi
docker-stubs/models/plugins.pyi
docker-stubs/models/resource.pyi
docker-stubs/models/secrets.pyi
docker-stubs/models/services.pyi
docker-stubs/models/swarm.pyi
docker-stubs/models/volumes.pyi
docker-stubs/tls.pyi
docker-stubs/transport/__init__.pyi
docker-stubs/transport/basehttpadapter.pyi
docker-stubs/transport/npipeconn.pyi
docker-stubs/transport/npipesocket.pyi
docker-stubs/transport/sshconn.pyi
docker-stubs/transport/unixconn.pyi
docker-stubs/types/__init__.pyi
docker-stubs/types/_io.pyi
docker-stubs/types/base.pyi
docker-stubs/types/containers.pyi
docker-stubs/types/daemon.pyi
docker-stubs/types/healthcheck.pyi
docker-stubs/types/misc_types.pyi
docker-stubs/types/networks.pyi
docker-stubs/types/services.pyi
docker-stubs/types/swarm.pyi
docker-stubs/utils/__init__.pyi
docker-stubs/utils/build.pyi
docker-stubs/utils/config.pyi
docker-stubs/utils/decorators.pyi
docker-stubs/utils/fnmatch.pyi
docker-stubs/utils/json_stream.pyi
docker_stubs-0.1.1a0.dist-info/METADATA
docker_stubs-0.1.1a0.dist-info/WHEEL
docker_stubs-0.1.1a0.dist-info/RECORD
